poppy/__init__.py
poppy/pop/__init__.py
poppy/pop/alembic/__init__.py
poppy/pop/alembic/env.py
poppy/pop/alembic/helpers.py
poppy/pop/alembic/script.py.mako
poppy/pop/commands/__init__.py
poppy/pop/commands/db.py
poppy/pop/commands/master.py
poppy/pop/commands/migration.py
poppy/pop/commands/test.py
poppy/pop/commands/web_admin.py
poppy/pop/db_connector.py
poppy/pop/descriptor.json
poppy/pop/json_schemas/__init__.py
poppy/pop/json_schemas/config-schema.json
poppy/pop/json_schemas/pipeline-descriptor-schema.json
poppy/pop/json_schemas/plugin-descriptor-schema.json
poppy/pop/loop.py
poppy/pop/migration.py
poppy/pop/models/__init__.py
poppy/pop/models/alembic_script_extra.py
poppy/pop/models/job.py
poppy/pop/models/versions/poppy_pop_0001_initial_.py
poppy/pop/models/versions/poppy_pop_0002_version_num_.py
poppy/pop/plugins.py
poppy/pop/pop.py
poppy/pop/scripts/__init__.py
poppy/pop/scripts/create_migrator.sql
poppy/pop/scripts/drop_migrator.sql
poppy/pop/scripts/scripts.py
poppy/pop/tasks.py
poppy/pop/tests/__init__.py
poppy/pop/tests/test_db_cmd.py
poppy/pop/tools.py
poppy_pop-0.12.3.dist-info/LICENSE
poppy_pop-0.12.3.dist-info/METADATA
poppy_pop-0.12.3.dist-info/WHEEL
poppy_pop-0.12.3.dist-info/entry_points.txt
poppy_pop-0.12.3.dist-info/RECORD
