Metadata-Version: 2.3
Name: poppy-pop
Version: 0.12.3
Summary: POPPY Operation Plugin (POP)
Home-page: https://gitlab.obspm.fr/POPPy/POP
License: CeCILL 2.1
Author: Xavier Bonnin
Author-email: xavier.bonnin@obspm.fr
Requires-Python: >=3.9,<4
Classifier: License :: Other/Proprietary License
Classifier: Programming Language :: Python :: 3
Classifier: Programming Language :: Python :: 3.9
Classifier: Programming Language :: Python :: 3.10
Classifier: Programming Language :: Python :: 3.11
Classifier: Programming Language :: Python :: 3.12
Classifier: Programming Language :: Python :: 3.13
Requires-Dist: poppy-core (>=0.12.2)
Requires-Dist: toml
Project-URL: Repository, https://gitlab.obspm.fr/POPPy/POP
